plone.recipe.alltests-1.5.2-py2.7-nspkg.pth
plone/recipe/alltests/__init__.py
plone/recipe/alltests/runner.py
plone.recipe.alltests-1.5.2.dist-info/METADATA
plone.recipe.alltests-1.5.2.dist-info/WHEEL
plone.recipe.alltests-1.5.2.dist-info/entry_points.txt
plone.recipe.alltests-1.5.2.dist-info/namespace_packages.txt
plone.recipe.alltests-1.5.2.dist-info/top_level.txt
plone.recipe.alltests-1.5.2.dist-info/RECORD
