Metadata-Version: 2.1
Name: plone.recipe.alltests
Version: 1.5.2
Summary: Buildout recipe for running tests isolated at package boundaries
Home-page: https://pypi.org/project/plone.recipe.alltests
Author: Hanno Schlichting
Author-email: hanno@hannosch.eu
License: ZPL 2.1
Keywords: zope2 buildout
Platform: UNKNOWN
Classifier: Development Status :: 5 - Production/Stable
Classifier: License :: OSI Approved :: Zope Public License
Classifier: Framework :: Buildout
Classifier: Framework :: Plone
Classifier: Framework :: Plone :: 4.3
Classifier: Framework :: Plone :: 5.0
Classifier: Framework :: Plone :: 5.1
Classifier: Framework :: Plone :: 5.2
Classifier: Framework :: Plone :: Core
Classifier: Framework :: Zope2
Classifier: Framework :: Zope :: 4
Classifier: Programming Language :: Python
Classifier: Programming Language :: Python :: 2.6
Classifier: Programming Language :: Python :: 2.7
Classifier: Programming Language :: Python :: 3.6
Classifier: Programming Language :: Python :: 3.7
Classifier: Programming Language :: Python :: 3.8
Requires-Dist: zc.buildout
Requires-Dist: setuptools
Requires-Dist: zc.recipe.egg
